blokus_engine-0.3.6.dist-info/METADATA
blokus_engine-0.3.6.dist-info/WHEEL
blokus_self_play/__init__.py
blokus_self_play/blokus_self_play.cpython-313t-arm-linux-gnueabihf.so
blokus_engine-0.3.6.dist-info/RECORD
