Metadata-Version: 2.4
Name: blokus_engine
Version: 0.3.6
Classifier: Programming Language :: Rust
Classifier: Programming Language :: Python :: Implementation :: CPython
Classifier: Programming Language :: Python :: Implementation :: PyPy
Author: Alex Racapé
Requires-Python: >=3.7
